setup.py
tests/__init__.py
tests/test_sqlalchemy.py
zwb_data/__init__.py
zwb_data/sqlalchemy_utils.py
zwb_data.egg-info/PKG-INFO
zwb_data.egg-info/SOURCES.txt
zwb_data.egg-info/dependency_links.txt
zwb_data.egg-info/requires.txt
zwb_data.egg-info/top_level.txt