Metadata-Version: 1.0
Name: zwb-data
Version: 1.0.0
Summary: zwb_data
Home-page: https://github.com/weibin268/zwb_data
Author: zhuang weibin
Author-email: 448075543@qq.com
License: UNKNOWN
Keywords: util
Platform: any
